IPYNBrendererYT/__init__.py
IPYNBrendererYT/custom_exception.py
IPYNBrendererYT/logger.py
IPYNBrendererYT/youtube.py
IPYNBrendererYT-0.0.5.dist-info/LICENSE
IPYNBrendererYT-0.0.5.dist-info/METADATA
IPYNBrendererYT-0.0.5.dist-info/WHEEL
IPYNBrendererYT-0.0.5.dist-info/top_level.txt
IPYNBrendererYT-0.0.5.dist-info/RECORD
